Workbook

Sheet Hoja2
A2: Estructura de hierro | K2: =K30+K40+K51 -> 2496.1152 | L2: kg | M2: 4.5 | N2: 1 | O2: =N2*M2*K2 -> 11232.518 | Q2: =O2*380 -> 4268357 | R2: =K2*1.3 -> 3244.9498 | S2: =R2*380 -> 1233080.9
A4: anclajes metalicos para T2-T2 (vigas F - Vigas PB) | O4: =115*2700 -> 310500 | Q4: =10*12000*6 -> 720000
Q5: =Q4*3 -> 2160000
A6: descripcion | B6: cantidad | D6: unidades | E6: total sup | G6: peso x m2 | I6: total peso | K6: =200*14500 -> 2900000 | O6: =SUM(O2:O4) -> 321732.52
A7: CHAPA 200x100x4,76 | B7: 0.02 | C7: m2 | D7: 24 | E7: =D7*B7 -> 0.48 | F7: m2 | G7: 37.68 | H7: kg/m2 | I7: =G7*E7 -> 18.0864 | J7: kg
A8: CHAPA 200x200x4,76 | B8: 0.04 | C8: m2 | D8: 12 | E8: =D8*B8 -> 0.48 | F8: m2 | G8: 37.68 | H8: kg/m2 | I8: =G8*E8 -> 18.0864 | J8: kg
A9: hierro liso Ø 12 | B9: 0.75 | C9: mL | D9: 24 | E9: =B9*D9 -> 18 | F9: mL | G9: 0.888 | H9: kg/mL | I9: =G9*E9 -> 15.984 | J9: kg | O9: =700000/380 -> 1842.1053
O10: =2500000/380 -> 6578.9474
A11: cruces de san andres T2-T2 | O11: =(O10+O9)*1.7 -> 14315.789 | Q11: =(O11-O10-O9)*380 -> 2240000
A12: hierro ANG 2 1/4" x 3/16" | B12: 30.4 | C12: mL | D12: 1.05 | E12: =B12*D12 -> 31.92 | F12: mL | G12: 4.1 | H12: kg/mL | I12: =G12*E12 -> 130.872 | J12: kg
A14: TOTAL anclajes met y cruces de SA T2-T2 (vigas F - Vigas PB)
A16: Insertos para CM1
A18: descripcion | B18: cantidad | D18: unidades | E18: total sup | G18: peso x m2 | I18: total peso | O18: =17*3.5 -> 59.5
A19: CHAPA 150x150x4,76 (CM1) | B19: 0.0225 | C19: m2 | D19: 55 | E19: =D19*B19 -> 1.2375 | F19: m2 | G19: 37.68 | H19: kg/m2 | I19: =G19*E19 -> 46.629 | J19: kg
A20: hierro liso Ø 10 | B20: 1.8 | C20: m2 | D20: 55 | E20: =D20*B20 -> 99 | F20: m2 | G20: 0.617 | H20: kg/m2 | I20: =G20*E20 -> 61.083 | J20: kg
A21: hierro liso Ø 6 | B21: 0.92 | C21: mL | D21: 55 | E21: =B21*D21 -> 50.6 | F21: mL | G21: 0.222 | H21: kg/mL | I21: =G21*E21 -> 11.2332 | J21: kg
A23: TOTAL anclajes insertos para CM1 | L23: kg
A25: Columnas CM200-80-2mm
A27: descripcion | B27: cantidad | D27: unidades | E27: total sup | G27: peso x m2 | I27: total peso
A28: CM planta 1er p (C200/80/25/2,5) | B28: 19 | D28: =3.5*2 -> 7 | E28: =D28*B28 -> 133 | F28: mL | G28: 7.72 | H28: kg/mL | I28: =G28*E28 -> 1026.76 | J28: kg
A30: TOTAL anclajes met en vigas de fundaciones para recibir CM1 | K30: =SUM(I28:I29) -> 1026.76 | L30: kg
A32: Refuerzos DM1
A34: descripcion | B34: cantidad | D34: unidades | E34: total sup | G34: peso x m2 | I34: total peso
A35: hierro liso Ø 12 | B35: 12 | C35: mL | D35: 3 | E35: =B35*D35 -> 36 | F35: mL | G35: 0.888 | H35: kg/mL | I35: =G35*E35 -> 31.968 | J35: kg
A36: CHAPA 300x300x6,4 | B36: =0.3*0.3 -> 0.09 | C36: m2 | D36: 17 | E36: =D36*B36 -> 1.53 | F36: m2 | G36: =25.12*2 -> 50.24 | H36: kg/m2 | I36: =G36*E36 -> 76.8672 | J36: kg
A40: TOTAL anclajes met en vigas de fundaciones para recibir CM1 | K40: =SUM(I34:I39) -> 108.8352 | L40: kg
A42: Vigas VM
A44: descripcion | B44: cantidad | D44: unidades | E44: total sup | G44: peso x m2 | I44: total peso
A45: VM de Contorno (C200/80/25/2,5) | B45: =51*2 -> 102 | C45: mL | D45: 1 | E45: =D45*B45 -> 102 | F45: mL | G45: 7.72 | H45: kg/mL | I45: =G45*E45 -> 787.44 | J45: kg
A46: VM IPN 200 | B46: 14 | C46: mL | D46: 1 | E46: =D46*B46 -> 14 | F46: mL | G46: 26.2 | H46: kg/mL | I46: =G46*E46 -> 366.8 | J46: kg
A47: VM CUBIERTA (C140/50/15/2) | B47: 0 | C47: mL | D47: 1 | E47: =D47*B47 -> 0 | F47: mL | G47: 4.51 | H47: kg/mL | I47: =G47*E47 -> 0 | J47: kg | N47: =12*12 -> 144 | O47: =N47/2 -> 72
A48: planchuela 3/4" *x 1/8" | B48: =B47/0.5*0.1 -> 0 | C48: mL | D48: 1 | E48: =D48*B48 -> 0 | F48: mL | G48: 0.48 | H48: kg/mL | I48: =G48*E48 -> 0 | J48: kg | O48: =8000*O47 -> 576000
A49: hierro angulo 2" x 3/16" | B49: =(20*0.8*3)+31*0.15*2 -> 57.3 | C49: mL | D49: 1 | E49: =D49*B49 -> 57.3 | F49: mL | G49: 3.6 | H49: kg/mL | I49: =G49*E49 -> 206.28 | J49: kg
A51: TOTAL VM1-VM3 | K51: =SUM(I45:I50) -> 1360.52 | L51: kg
A53: CUBIERTA
A55: descripcion | B55: cantidad | D55: unidades | E55: total sup | G55: peso x m2 | I55: total peso
A56: CoC (C140/60/20/2) | B56: 308 | C56: mL | D56: 1 | E56: =D56*B56 -> 308 | F56: mL | G56: =4.51 -> 4.51 | H56: kg/mL | I56: =G56*E56 -> 1389.08 | J56: kg
A57: PRESILLAS CADA 700MM | B57: 2.97 | C57: m2 | D57: 1 | E57: =D57*B57 -> 2.97 | F57: mL | G57: 15.58 | H57: kg/mL | I57: =G57*E57 -> 46.2726 | J57: kg
A58: CHAPA UNION CoC CON VM1/3 | B58: 0.018 | C58: m2 | D58: 123 | E58: =D58*B58 -> 2.214 | F58: mL | G58: 25.12 | H58: kg/m2 | I58: =G58*E58 -> 55.61568 | J58: kg
A60: TOTAL CUBIERTA | L60: kg
A63: ESCALERA
A64: Insertos para CM2
A66: descripcion | B66: cantidad | D66: unidades | E66: total sup | G66: peso x m2 | I66: total peso
A67: DM1 nivel fund-pb (70/70/2) | E67: 9 | F67: mL | G67: 4.29 | H67: kg/mL | I67: =G67*E67 -> 38.61 | J67: kg
A68: CHAPA 150x150x3,2 | B68: 0.0225 | C68: m2 | D68: 12 | E68: =D68*B68 -> 0.27 | F68: m2 | G68: 25.12 | H68: kg/m2 | I68: =G68*E68 -> 6.7824 | J68: kg
A69: DM1 nivel pb-2/2pb (70/70/2) | E69: 12 | F69: mL | G69: 4.29 | H69: kg/mL | I69: =G69*E69 -> 51.48 | J69: kg
A70: CHAPA 150x150x3,2 | B70: 0.0225 | C70: m2 | D70: 12 | E70: =D70*B70 -> 0.27 | F70: m2 | G70: 25.12 | H70: kg/m2 | I70: =G70*E70 -> 6.7824 | J70: kg
A71: DM1 nivel 1/2-pa (70/70/2) | E71: 18 | F71: mL | G71: 4.29 | H71: kg/mL | I71: =G71*E71 -> 77.22 | J71: kg
A72: CHAPA 150x150x3,2 | B72: 0.0225 | C72: m2 | D72: 12 | E72: =D72*B72 -> 0.27 | F72: m2 | G72: 25.12 | H72: kg/m2 | I72: =G72*E72 -> 6.7824 | J72: kg | M72: =1.2*0.3 -> 0.36
A73: COLUMNAS CM2 IPN 140 | B73: 6.6 | C73: mL | D73: 6 | E73: =D73*B73 -> 39.6 | F73: mL | G73: 14.3 | H73: kg/mL | I73: =G73*E73 -> 566.28 | J73: kg
A74: VIGAS VM2 IPN 140 | B74: 6 | C74: mL | D74: 1 | E74: =D74*B74 -> 6 | F74: mL | G74: 14.3 | H74: kg/mL | I74: =G74*E74 -> 85.8 | J74: kg
A75: VIGAS VM4 IPN 100 | B75: =6.1+4.7+2.6+2.6+1.3+4.1 -> 21.4 | C75: mL | D75: 1 | E75: =D75*B75 -> 21.4 | F75: mL | G75: 8.3 | H75: kg/mL | I75: =G75*E75 -> 177.62 | J75: kg
A76: VIGAS VME IPN 100 | B76: =2.4*4 -> 9.6 | C76: mL | D76: 1 | E76: =D76*B76 -> 9.6 | F76: mL | G76: 8.3 | H76: kg/mL | I76: =G76*E76 -> 79.68 | J76: kg
A77: Escalon Metal Despl 250/30/12 | B77: 0.36 | C77: m2 | D77: 14 | E77: =D77*B77 -> 5.04 | F77: m2 | G77: 10.8 | H77: kg/m2 | I77: =G77*E77 -> 54.432 | J77: kg | M77: =1.2*0.3 -> 0.36
A78: Escalon Planchuela 270/32/4,76 | B78: 0.6 | C78: mL | D78: 14 | E78: =D78*B78 -> 8.4 | F78: mL | G78: 1.1 | H78: kg/mL | I78: =G78*E78 -> 9.24 | J78: kg
A79: Escalon Angulo 38/38/4,76 | B79: 3 | C79: mL | D79: 14 | E79: =B79*D79 -> 42 | F79: mL | G79: 2.2 | H79: kg/mL | I79: =G79*E79 -> 92.4 | J79: kg
A80: Descanso Metal Despl 250/30/12 | B80: 2.9 | C80: m2 | D80: 1 | E80: =D80*B80 -> 2.9 | F80: m2 | G80: 10.8 | H80: kg/m2 | I80: =G80*E80 -> 31.32 | J80: kg | M80: =1.2*0.3 -> 0.36
A81: Descanso Angulo 38/38/4,76 | B81: 4.8 | C81: mL | D81: 1 | E81: =B81*D81 -> 4.8 | F81: mL | G81: 2.2 | H81: kg/mL | I81: =G81*E81 -> 10.56 | J81: kg | O81: 1100 | P81: 1.3 | Q81: =P81*O81*201 -> 287430
O82: 1.95
A83: TOTAL anclajes insertos para CM2 | L83: kg | O83: =O82*O81 -> 2145 | P83: =O83*201 -> 431145 | Q83: =P83+Q81 -> 718575
A85: PASARELA
A87: descripcion | B87: cantidad | D87: unidades | E87: total sup | G87: peso x m2 | I87: total peso
A88: CoP (C140/60/20/2) | B88: 52 | C88: mL | D88: 1 | E88: =D88*B88 -> 52 | F88: mL | G88: =4.51 -> 4.51 | H88: kg/mL | I88: =G88*E88 -> 234.52 | J88: kg | M88: =B88/0.7 -> 74.285714 | N88: =M88*0.06*0.12 -> 0.53485714
A89: PRESILLAS CADA 700MM | B89: 0.54 | C89: m2 | D89: 1 | E89: =D89*B89 -> 0.54 | F89: m2 | G89: 15.58 | H89: kg/m2 | I89: =G89*E89 -> 8.4132 | J89: kg
A90: CHAPA UNION CoP CON VM1/3 | B90: 0.01 | C90: m2 | D90: 123 | E90: =D90*B90 -> 1.23 | F90: mL | G90: 25.12 | H90: kg/m2 | I90: =G90*E90 -> 30.8976 | J90: kg
A92: TOTAL PASARELA | L92: kg
A94: REFUERZOS C SAN ANDRES CUBIERTA
A96: descripcion | B96: cantidad | D96: unidades | E96: total sup | G96: peso x m2 | I96: total peso
A97: CHAPA 120x100x4,76 | B97: =0.12*0.1 -> 0.012 | C97: m2 | D97: 32 | E97: =D97*B97 -> 0.384 | F97: m2 | G97: 37.68 | H97: kg/m2 | I97: =G97*E97 -> 14.46912 | J97: kg
A98: hierro liso Ø 8 | B98: 78.2 | C98: mL | D98: 1 | E98: =B98*D98 -> 78.2 | F98: mL | G98: 0.395 | H98: kg/mL | I98: =G98*E98 -> 30.889 | J98: kg
A100: TOTAL REFUERZOS C SAN ANDRES CUBIERTA | L100: kg
A102: DEPOSITO CONTIGUO ESCALERA
A104: descripcion | B104: cantidad | D104: unidades | E104: total sup | G104: peso x m2 | I104: total peso
A105: VIGAS VM2 IPN 140 | B105: 9 | C105: mL | D105: 1 | E105: =D105*B105 -> 9 | F105: mL | G105: 14.3 | H105: kg/mL | I105: =G105*E105 -> 128.7 | J105: kg
A106: VM1 (C100/50/15/2) | B106: 25.4 | C106: mL | D106: 1 | E106: =D106*B106 -> 25.4 | F106: mL | G106: =2*3.41 -> 6.82 | H106: kg/mL | I106: =G106*E106 -> 173.228 | J106: kg
A107: CoD (C100/50/15/2) | B107: 17.5 | C107: mL | D107: 1 | E107: =D107*B107 -> 17.5 | F107: mL | G107: =2*3.41 -> 6.82 | H107: kg/mL | I107: =G107*E107 -> 119.35 | J107: kg
A108: PRESILLAS CADA 700MM | B108: 0.18 | C108: m2 | D108: 1 | E108: =D108*B108 -> 0.18 | F108: m2 | G108: 15.58 | H108: kg/m2 | I108: =G108*E108 -> 2.8044 | J108: kg
A109: C1 (C100/50/15/2) | B109: 12.8 | C109: mL | D109: 55 | E109: =D109*B109 -> 704 | F109: mL | G109: =2*3.41 -> 6.82 | H109: kg/mL | I109: =G109*E109 -> 4801.28 | J109: kg
A111: TOTAL DEPOSITO CONTIGUO ESCALERA | L111: kg
A113: CUBIERTA ESCALERA Y DEPOSITO
A115: descripcion | B115: cantidad | D115: unidades | E115: total sup | G115: peso x m2 | I115: total peso
A116: CHAPA UNION Coe CON VM1/3 | B116: 0.018 | C116: m2 | D116: 84 | E116: =D116*B116 -> 1.512 | F116: mL | G116: 25.12 | H116: kg/m2 | I116: =G116*E116 -> 37.98144 | J116: kg
A118: TOTAL CUBIERTA | L118: kg

Sheet Hoja6
O1: =M1/N1 -> #DIV/0!
A2: 1.2 | B2: Partida | C2: Muros bloques de retak 20/50 | D2: M2
B3: Mano de obra | C3: OFICIAL ESPECIALIZADO | D3: hs | E3: 0 | F3: =80000/9+5789 -> 14677.889 | G3: =E3*F3 -> 0
B4: Mano de obra | C4: OFICIAL | D4: hs | E4: 0.8 | F4: =50000/9+5789 -> 11344.556 | G4: =E4*F4 -> 9075.6444
B5: Mano de obra | C5: MEDIO OFICIAL | D5: hs | F5: =45000/9+5789 -> 10789 | G5: =E5*F5 -> 0
B6: Mano de obra | C6: AYUDANTE | D6: hs | E6: 0.7 | F6: =35000/9+5768 -> 9656.8889 | G6: =E6*F6 -> 6759.8222
B7: Mano de obra | C7: AYUDA DE GREMIO ayudante | D7: hs | F7: =F6 -> 9656.8889 | G7: =E7*F7 -> 0
B8: SUBTOTAL MANO DE OBRA (A) | G8: =SUM(G3:G7) -> 15835.467
B9: Material | C9: Pegamento Retak | D9: kg | E9: 6.25 | F9: 600 | G9: =E9*F9 -> 3750
B10: Material | C10: Bloque Retak | D10: u | E10: =8*1.05 -> 8.4 | F10: 6000 | G10: =E10*F10 -> 50400
B11: Material | G11: =E11*F11 -> 0
B12: Material | G12: =E12*F12 -> 0
B13: Material | G13: =E13*F13 -> 0
B14: Material | G14: =E14*F14 -> 0
B15: Material | G15: =E15*F15 -> 0
B16: Material | G16: =E16*F16 -> 0
B17: Material | G17: =E17*F17 -> 0
B18: Material | G18: =E18*F18 -> 0
B19: Material | G19: =E19*F19 -> 0
B20: Material
B21: Material
B22: Material
B23: SUBTOTAL MATERIAL (B) | G23: =SUM(G9:G22) -> 54150
B25: 1 | C25: MANO DE OBRA | D25: TOTAL (A) | G25: =G8 -> 15835.467
B26: 2 | C26: MATERIALES | D26: TOTAL (B) | G26: =G23 -> 54150
B27: 3 | C27: EQUIPOS | D27: TOTAL (C)
B28: 4 | C28: COSTO - COSTO | D28: (1 + 2 + 3) | G28: =SUM(G25:G27) -> 69985.467 | I28: =G28*1.95 -> 136471.66
B29: 5 | C29: GASTOS GENERALES | D29: D% x (4) | E29: 0.25 | G29: =+G28*E29 -> 17496.367
B30: 6 | C30: COSTO - COSTO + GASTOS GENERALES | D30: (4 + 5) | G30: =G29+G28 -> 87481.833
B31: 7 | C31: IMPREVISTOS Y EVENTUALIDADES | D31: E% x (6) | E31: 0.07 | G31: =+G30*E31 -> 6123.7283
B32: 8 | C32: EPP-SEGURIDAD | D32: F% x (6) | E32: 0.05 | G32: =G30*E32 -> 4374.0917
B33: 9 | C33: BENEFICIO | D33: G% x (6) | E33: 0.2 | G33: =G30*E33 -> 17496.367
B34: 10 | C34: COSTO TOTAL DEL TRABAJO | D34: (6 + 7 + 8 + 9) | G34: =G33+G32+G31+G30 -> 115476.02
B35: 11 | C35: COSTO TOTAL DEL TRABAJO SIN MATERIALES | D35: (10 - 1) | G35: =G34-G26 -> 61326.02
B36: 12 | C36: IMPUESTOS (IIBB - GANANCIAS) | D36: V % x (9) | E36: 0.1 | G36: =G34*E36 -> 11547.602
B37: 13 | C37: GANANCIAS | E37: 0 | G37: =G33*E37 -> 0
B39: 16 | C39: PRECIO UNITARIO DE APLICACIÓN SIN MATERIALES | D39: (10 + 12 + 13) | G39: =G35+G36+G37 -> 72873.622 | J39: 1200 | K39: =G39/J39 -> 60.728018
A41: 1.2 | B41: Partida | C41: EXCAVACIONES MANUALES BASES | D41: M3
B42: Mano de obra | C42: OFICIAL ESPECIALIZADO | D42: hs | F42: =F3 -> 14677.889 | G42: =E42*F42 -> 0
B43: Mano de obra | C43: OFICIAL | D43: hs | E43: 0 | F43: =F4 -> 11344.556 | G43: =E43*F43 -> 0
B44: Mano de obra | C44: MEDIO OFICIAL | D44: hs | F44: =F5 -> 10789 | G44: =E44*F44 -> 0
B45: Mano de obra | C45: AYUDANTE | D45: hs | E45: 10.15 | F45: =F6 -> 9656.8889 | G45: =E45*F45 -> 98017.422
B46: Mano de obra | C46: AYUDA DE GREMIO ayudante | D46: hs | E46: 0 | F46: =F7 -> 9656.8889 | G46: =E46*F46 -> 0
B47: SUBTOTAL MANO DE OBRA (A) | G47: =SUM(G42:G46) -> 98017.422
B48: Material | G48: =E48*F48 -> 0
B49: Material | G49: =E49*F49 -> 0
B50: Material | G50: =E50*F50 -> 0
B51: Material | G51: =E51*F51 -> 0
B52: Material | G52: =E52*F52 -> 0
B53: Material | G53: =E53*F53 -> 0
B54: Material | G54: =E54*F54 -> 0
B55: Material | G55: =E55*F55 -> 0
B56: Material | G56: =E56*F56 -> 0
B57: Material | G57: =E57*F57 -> 0
B58: Material | G58: =E58*F58 -> 0
B59: Material
B60: Material
B61: Material
B62: SUBTOTAL MATERIAL (B) | G62: =SUM(G48:G61) -> 0
B64: 1 | C64: MANO DE OBRA | D64: TOTAL (A) | G64: =G47 -> 98017.422
B65: 2 | C65: MATERIALES | D65: TOTAL (B) | G65: =G62 -> 0
B66: 3 | C66: EQUIPOS | D66: TOTAL (C)
B67: 4 | C67: COSTO - COSTO | D67: (1 + 2 + 3) | G67: =SUM(G64:G66) -> 98017.422
B68: 5 | C68: GASTOS GENERALES | D68: D% x (4) | E68: =E29 -> 0.25 | G68: =+G67*E68 -> 24504.356
B69: 6 | C69: COSTO - COSTO + GASTOS GENERALES | D69: (4 + 5) | E69: =E30 -> 0 | G69: =G68+G67 -> 122521.78
B70: 7 | C70: IMPREVISTOS Y EVENTUALIDADES | D70: E% x (6) | E70: =E31 -> 0.07 | G70: =+G69*E70 -> 8576.5244
B71: 8 | C71: EPP-SEGURIDAD | D71: F% x (6) | E71: =E32 -> 0.05 | G71: =G69*E71 -> 6126.0889
B72: 9 | C72: BENEFICIO | D72: G% x (6) | E72: =E33 -> 0.2 | G72: =G69*E72 -> 24504.356
B73: 10 | C73: COSTO TOTAL DEL TRABAJO | D73: (6 + 7 + 8 + 9) | E73: =E34 -> 0 | G73: =G72+G71+G70+G69 -> 161728.75
B74: 11 | C74: COSTO TOTAL DEL TRABAJO SIN MATERIALES | D74: (10 - 1) | E74: =E35 -> 0 | G74: =G73-G65 -> 161728.75
B75: 12 | C75: IMPUESTOS (IIBB - GANANCIAS) | D75: V % x (9) | E75: =E36 -> 0.1 | G75: =G73*E75 -> 16172.875
B76: 13 | C76: GANANCIAS | E76: =E37 -> 0 | G76: =G72*E76 -> 0
B78: 16 | C78: PRECIO UNITARIO DE APLICACIÓN SIN MATERIALES | D78: (10 + 12 + 13) | G78: =G74+G75+G76 -> 177901.62 | J78: =J39 -> 1200 | K78: =G78/J78 -> 148.25135
A80: 1.2 | B80: Partida | C80: ROTURA DE ROCA | D80: M3
B81: Mano de obra | C81: OFICIAL ESPECIALIZADO | D81: hs | F81: =F42 -> 14677.889 | G81: =E81*F81 -> 0
B82: Mano de obra | C82: OFICIAL | D82: hs | E82: 0 | F82: =F43 -> 11344.556 | G82: =E82*F82 -> 0
B83: Mano de obra | C83: MEDIO OFICIAL | D83: hs | F83: =F44 -> 10789 | G83: =E83*F83 -> 0
B84: Mano de obra | C84: AYUDANTE | D84: hs | E84: 10.15 | F84: =F45 -> 9656.8889 | G84: =E84*F84 -> 98017.422
B85: Mano de obra | C85: AYUDA DE GREMIO ayudante | D85: hs | E85: 0 | F85: =F46 -> 9656.8889 | G85: =E85*F85 -> 0
B86: SUBTOTAL MANO DE OBRA (A) | G86: =SUM(G81:G85) -> 98017.422
B87: Material | G87: =E87*F87 -> 0
B88: Material | G88: =E88*F88 -> 0
B89: Material | G89: =E89*F89 -> 0
B90: Material | G90: =E90*F90 -> 0
B91: Material | G91: =E91*F91 -> 0
B92: Material | G92: =E92*F92 -> 0
B93: Material | G93: =E93*F93 -> 0
B94: Material | G94: =E94*F94 -> 0
B95: Material | G95: =E95*F95 -> 0
B96: Material | G96: =E96*F96 -> 0
B97: Material | G97: =E97*F97 -> 0
B98: Material
B99: Material
B100: Material
B101: SUBTOTAL MATERIAL (B) | G101: =SUM(G87:G100) -> 0
B103: 1 | C103: MANO DE OBRA | D103: TOTAL (A) | G103: =G86 -> 98017.422
B104: 2 | C104: MATERIALES | D104: TOTAL (B) | G104: =G101 -> 0
B105: 3 | C105: EQUIPOS | D105: TOTAL (C) | G105: 15000
B106: 4 | C106: COSTO - COSTO | D106: (1 + 2 + 3) | G106: =SUM(G103:G105) -> 113017.42 | I106: =G106*1.95 -> 220383.97
B107: 5 | C107: GASTOS GENERALES | D107: D% x (4) | E107: =E68 -> 0.25 | G107: =+G106*E107 -> 28254.356
...

Sheet Hoja8
D3: MATERIALES | I3: MANO DE OBRA | N3: MATERIALES | S3: MANO DE OBRA
C4: ESTRUCTURA | D4: hierro barra tn | E4: alambre kg | F4: tablas m2 | G4: tirantes m2 | H4: clavos kg | I4: hora oficial | J4: hora ayudante | M4: ESTRUCTURA | N4: hierro barra tn | O4: alambre kg | P4: tablas m2 | Q4: tirantes m2 | R4: clavos kg | S4: hora oficial | T4: hora ayudante
C5: BASES | D5: 0.06 | E5: 0.25 | I5: 6.15 | J5: 11.3 | M5: BASES | N5: =D5*D14 -> 0.066 | O5: =E5*E14 -> 0.275 | P5: =F5*F14 -> 0 | Q5: =G5*G14 -> 0 | R5: =H5*H14 -> 0 | S5: =I5*I14 -> 6.765 | T5: =J5*J14 -> 12.43
C6: COLUMNAS | D6: 0.085 | E6: 0.6 | F6: 2.5 | G6: 0.36 | H6: 2 | I6: 14.35 | J6: 1.71 | M6: COLUMNAS | N6: =D6*D15 -> 0.0935 | O6: =E6*E15 -> 0.66 | P6: =F6*F15 -> 2.75 | Q6: =G6*G15 -> 0.396 | R6: =H6*H15 -> 2.2 | S6: =I6*I15 -> 15.785 | T6: =J6*J15 -> 1.881
C7: LOSAS Y CORNISAS | D7: 0.08 | E7: 0.6 | F7: 3 | G7: 1 | H7: 1 | I7: 19.15 | J7: 18.05 | M7: LOSAS Y CORNISAS | N7: =D7*D16 -> 0.088 | O7: =E7*E16 -> 0.66 | P7: =F7*F16 -> 3.3 | Q7: =G7*G16 -> 1.1 | R7: =H7*H16 -> 1.1 | S7: =I7*I16 -> 21.065 | T7: =J7*J16 -> 19.855
C8: VIGAS | D8: 0.18 | E8: 0.84 | F8: 3.5 | G8: 1.35 | H8: 1.5 | I8: 32.15 | J8: 18.3 | M8: VIGAS | N8: =D8*D17 -> 0.198 | O8: =E8*E17 -> 0.924 | P8: =F8*F17 -> 3.85 | Q8: =G8*G17 -> 1.485 | R8: =H8*H17 -> 1.65 | S8: =I8*I17 -> 35.365 | T8: =J8*J17 -> 20.13
C9: DINTELES | D9: 0.06 | E9: 0.6 | F9: 3.3 | G9: 0.72 | H9: 1.2 | I9: 37 | J9: 21.9 | M9: DINTELES | N9: =D9*D18 -> 0.066 | O9: =E9*E18 -> 0.66 | P9: =F9*F18 -> 3.63 | Q9: =G9*G18 -> 0.792 | R9: =H9*H18 -> 1.32 | S9: =I9*I18 -> 40.7 | T9: =J9*J18 -> 24.09
C10: TABIQUES | D10: 0.07 | E10: 0.5 | F10: 3.3 | G10: 0.26 | H10: 1.7 | I10: 30 | J10: 25 | M10: TABIQUES | N10: =D10*D19 -> 0.077 | O10: =E10*E19 -> 0.55 | P10: =F10*F19 -> 3.63 | Q10: =G10*G19 -> 0.286 | R10: =H10*H19 -> 1.87 | S10: =I10*I19 -> 33 | T10: =J10*J19 -> 27.5
C11: ENCADENADOS | D11: 0.05 | E11: 0.4 | F11: 2.5 | H11: 1.1 | I11: 25 | J11: 12.5 | M11: ENCADENADOS | N11: =D11*D20 -> 0.0525 | O11: =E11*E20 -> 0.42 | P11: =F11*F20 -> 2.625 | Q11: =G11*G20 -> 0 | R11: =H11*H20 -> 1.155 | S11: =I11*I20 -> 26.25 | T11: =J11*J20 -> 13.125
C12: ESCALERAS | D12: 0.055 | E12: 0.45 | F12: 2 | G12: 0.78 | H12: 1.7 | I12: 39.5 | J12: 22.5 | M12: =C12 -> ESCALERAS | N12: =D12*D21 -> 0.055 | O12: =E12*E21 -> 0.45 | P12: =F12*F21 -> 2 | Q12: =G12*G21 -> 0.78 | R12: =H12*H21 -> 1.7 | S12: =I12*I21 -> 39.5 | T12: =J12*J21 -> 22.5
D14: 1.1 | E14: =D14 -> 1.1 | F14: =E14 -> 1.1 | G14: =F14 -> 1.1 | H14: =G14 -> 1.1 | I14: =H14 -> 1.1 | J14: =I14 -> 1.1
D15: 1.1 | E15: =D15 -> 1.1 | F15: =E15 -> 1.1 | G15: =F15 -> 1.1 | H15: =G15 -> 1.1 | I15: =H15 -> 1.1 | J15: =I15 -> 1.1
D16: 1.1 | E16: =D16 -> 1.1 | F16: =E16 -> 1.1 | G16: =F16 -> 1.1 | H16: =G16 -> 1.1 | I16: =H16 -> 1.1 | J16: =I16 -> 1.1
D17: 1.1 | E17: =D17 -> 1.1 | F17: =E17 -> 1.1 | G17: =F17 -> 1.1 | H17: =G17 -> 1.1 | I17: =H17 -> 1.1 | J17: =I17 -> 1.1
D18: 1.1 | E18: =D18 -> 1.1 | F18: =E18 -> 1.1 | G18: =F18 -> 1.1 | H18: =G18 -> 1.1 | I18: =H18 -> 1.1 | J18: =I18 -> 1.1
D19: 1.1 | E19: =D19 -> 1.1 | F19: =E19 -> 1.1 | G19: =F19 -> 1.1 | H19: =G19 -> 1.1 | I19: =H19 -> 1.1 | J19: =I19 -> 1.1
D20: 1.05 | E20: =D20 -> 1.05 | F20: =E20 -> 1.05 | G20: =F20 -> 1.05 | H20: =G20 -> 1.05 | I20: =H20 -> 1.05 | J20: =I20 -> 1.05
D21: 1 | E21: =D21 -> 1 | F21: =E21 -> 1 | G21: =F21 -> 1 | H21: =G21 -> 1 | I21: =H21 -> 1 | J21: =I21 -> 1

Sheet COMP Y PRES 2
A1: EMPRESA CONSTRUCTORA GRUPO SL SAS
A2: San Carlos de Bariloche, 23 de MARZO de 2025
A3: De nuestra mayor consideración: Tenemos el agrado de elevar para vuestra consideración la siguiente Cotización sobre: Construcción Vivienda unifamiliar - Barrio Belgrano - SAN CARLOS DE BARILOCHE
A5: Monto Total de la Obra expresada en dolares: .................................................................... | F5: =F29 -> 25154813
B6: SON DOLARES CUARENTA Y SIETE MIL SEISCIENTOS CUARENTA Y UNO CON 41/100
A9: Valor expreado en dolares blue. - Consideraciones Generales Otros detalles no especificados en la documentación y que fuera objeto de análisis para el cálculo de la presente cotización, a definir y cotizar. - Obras a desarrollarse en Días hábiles APTOS: se consideran días de ejecución semanal en horario de 9hs. a 17hs. (a criterio técnico de nuestro personal, a coordinar), en condiciones normales de trabajo SEGURO a la Intemperie; otras “a nuestro exclusivo criterio”. - Todos los servicios necesarios para la realización de las obras en el sector OBRA (agua, electricidad, sanitarios), se consideran provistos por el cliente a pie de obra. - Nuestro personal calificado (por rubros) prestara sus servicios en obra, con máquinas y herramientas, EPP e infraestructura apta para las distintas tareas a realizar, a nuestro criterio.
A12: ITEM | B12: DESCRIPCION | C12: UND. | D12: CANT. | E12: P. UNITARIO | F12: P. TOTAL ITEM | I12: 1.3 | L12: 1360
A13: 1 - TAREAS PRELIMINARES
A14: 1.1 | B14: Obrador y Baño quimico (no se cotiza) | C14: Gl. | D14: 3 | E14: 269.16 | F14: =E14*D14 -> 807.48
A15: 1.2 | B15: Cerco de Obra | C15: Gl. | D15: 1 | E15: 1230 | F15: =E15*D15 -> 1230
D16: SUBTOTAL ITEM 1.- | F16: =SUM(F14:F15) -> 2037.48
A17: 2 - ESTRUCTURAS, EXCAVACIONES, HORMIGON FUNDACIONES, PLATEA CON VIGAS. | K17: =SUM(J18:J21) -> 102.1015
A18: 2.1 | B18: Demolicion de mamposterias, traslados de puertas, acarreo de demoliciones a contenedores (incluye contratacion de contenedores) | C18: Gl. | D18: =(55.54*3)*2.5+25*3 -> 491.55 | E18: =Hoja6!G429 -> 51093.553 | F18: =E18*D18 -> 25115036 | H18: 5.96 | I18: 1.85 | J18: =I18*H18 -> 11.026 | L18: =#REF! -> #REF! | M18: =L18*J18 -> #REF!
A19: 2.2 | B19: Bases aisladas (a 1m de profundidad) | C19: Gl. | D19: 6 | E19: =Hoja6!K195 -> 477.15307 | F19: =E19*D19 -> 2862.9184
A20: 2.3 | B20: Troncos de Columnas y columnas | C20: Gl. | D20: 4.59 | E20: =Hoja6!K234 -> 548.63919 | F20: =E20*D20 -> 2518.2539
A21: 2.4 | B21: Vigas -3,24, +/-0,00 y +4,2 | C21: Gl. | D21: 11.88 | E21: =Hoja6!K312 -> 1331.3828 | F21: =E21*D21 -> 15816.828 | H21: 49.23 | I21: =I18 -> 1.85 | J21: =I21*H21 -> 91.0755 | L21: =L18 -> #REF! | M21: =L21*J21 -> #REF!
A22: 2.5 | B22: Losas -3,24 y +/-0,00 | C22: Gl. | D22: 13.68 | E22: =Hoja6!K351 -> 927.4036 | F22: =E22*D22 -> 12686.881 | H22: 52.1 | I22: 1.45 | J22: =I22*H22 -> 75.545 | L22: =L21 -> #REF! | M22: =L22*J22 -> #REF!
A23: 2.6 | B23: Escaleras | C23: Gl. | D23: 2.62 | E23: =Hoja6!K390 -> 1222.3569 | F23: =E23*D23 -> 3202.5751
D24: SUBTOTAL ITEM 2.- | F24: =SUM(F18:F23) -> 25152123 | G24: =F24+F16 -> 25154161 | BC24: =BC21 -> 0
A25: 3 - VARIOS | J25: =37000/60 -> 616.66667 | BC25: =#REF! -> #REF!
A26: 3.1 | B26: Limpieza periodica y final de obra | C26: Gl. | D26: 1 | E26: 652.1 | F26: =E26*D26 -> 652.1 | H26: 1360 | I26: =F26*H26 -> 886856 | L26: 11 | M26: 1.95 | BC26: =#REF! -> #REF!
D27: SUBTOTAL ITEM 10.- | F27: =SUM(F26:F26) -> 652.1 | BC27: =#REF! -> #REF!
A29: TOTAL PRESUPUESTO | F29: =F27+F24+F16 -> 25154813 | G29: =F29/180 -> 139748.96 | H29: 1300 | I29: =H29*F29 -> 3.2701257e+10 | J29: =F29/60 -> 419246.88
A32: En la presente cotizacion no se incluyen valores de IVA.
A33: Los valores expresados en la presente cotizacion, de mano de obra, estan expresados en dólares BLUE
A34: La presente cotización tiene validez por 20 días.
A35: Forma de pago: 20% de anticipo y certificaciones quincenales según avance de obra.
AO46: PB
AO47: 1.5
AO48: 1.5
AO49: 0.8
AO50: 1.3
AO51: 3.2
AO52: 3.4
AO53: 1.3 | AP53: 0.8 | AQ53: 2.1 | AR53: 3 | AS53: =AP53*AQ53*AR53 -> 5.04
AO54: 2.55 | AP54: 0.9 | AQ54: 2.1 | AR54: 1 | AS54: =AP54*AQ54*AR54 -> 1.89
AO55: 2.45 | AP55: 2.3 | AQ55: 1.7 | AR55: 1 | AS55: =AP55*AQ55*AR55 -> 3.91
AO56: 3.8 | AP56: 0.9 | AQ56: 1.5 | AR56: 2 | AS56: =AP56*AQ56*AR56 -> 2.7
AO57: 0.7 | AP57: 2.3 | AQ57: 1.9 | AR57: 1 | AS57: =AP57*AQ57*AR57 -> 4.37
AO58: 3.5
AO59: 1.6
AO60: 1.6
AO61: 1.6
AO62: 3.5
AO63: 0.8
AO64: 2.2
AO65: 3.05
AO66: 1.5
AO67: 3.4
AO68: 1.9
AO69: 1.4 | AV69: ladrillos RETAK
AO70: =SUM(AO47:AO69) -> 48.55 | AP70: =AO70*2.42 -> 117.491 | AS70: =SUM(AS53:AS69) -> 17.91 | AU70: =AP70-AS70 -> 99.581 | AV70: =AU70*8 -> 796.648
AK71: =AP70+(AP78*2) -> 173.771
AO72: 57.764 | AP72: 2.42 | AQ72: =AP72*AO72 -> 139.78888
AO76: PA
AP77: 0.8 | AQ77: 2.1 | AR77: 3 | AS77: =AP77*AQ77*AR77 -> 5.04 | AV77: ladrillos RETAK
AO78: 10.05 | AP78: =AO78*2.8 -> 28.14 | AU78: =AP78-AS77 -> 23.1 | AV78: =AU78*8 -> 184.8
AP83: =AP78+AP70 -> 145.631

Sheet Hoja4
N1: =SUM(L3:R3) -> 2642901.5
I2: MANO DE OBRA | L2: GASTOS GENERALES 12% | M2: IMPREVISTOS Y EVENTUALIDADES 8% | N2: EPP y SEGURIDAD 5% | O2: BENEFICIO 15% | P2: INGRESOS BRUTOS 3% | Q2: GANANCIAS 35% | R2: INSUMIBLES | T2: Mano de Obra | Z2: Materiales | AA2: Gastos Generales | AB2: Imprev y event | AC2: EEP Seguridad | AD2: Beneficio | AE2: IIBB | AF2: Ganancias
I3: =SUM(I4:I1048576) -> #REF! | J3: =SUM(I3,L3,M3,N3,O3,P3,Q3,R3) -> #REF! | L3: =SUM(L4:L1048576) -> 514069.88 | M3: =SUM(M4:M1048576) -> 222708.05 | N3: =SUM(N4:N1048576) -> 133363.09 | O3: =SUM(O4:O1048576) -> 800049.31 | P3: =SUM(P4:P1048576) -> 211098.13 | Q3: =SUM(Q4:Q1048576) -> 209788.56 | R3: =SUM(R4:R1048576) -> 551824.5 | T3: =SUM(T4:T1048576) -> 401424.64 | V3: =SUM(V10:V87) -> 161189.58 | Y3: =SUM(Y10:Y87) -> 152004.91 | Z3: =SUM(Z4:Z1048576) -> 177569.8 | AA3: =SUM(AA4:AA1048576) -> 84229.394 | AB3: =SUM(AB4:AB1048576) -> 36528.667 | AC3: =SUM(AC4:AC1048576) -> 22255.782 | AD3: =SUM(AD4:AD1048576) -> 132120.27 | AE3: =SUM(AE4:AE1048576) -> 35779.344 | AF3: =SUM(AF4:AF1048576) -> 35557.383 | AI3: 4000 | AJ3: 1 | AK3: =AI3*AJ3 -> 4000 | AM3: 250 | AN3: 4 | AO3: =AN3*AM3*AJ3 -> 1000 | AQ3: =AO3+AK3 -> 5000
A4: 1.1 | B4: Partida | C4: CONTRAPISOS | D4: M2 | AI4: 3500 | AJ4: 2 | AK4: =AI4*AJ4 -> 7000 | AM4: 180 | AN4: 4 | AO4: =AN4*AM4*AJ4 -> 1440 | AQ4: =AO4+AK4 -> 8440
B5: Mano de obra | C5: OFICIAL ESPECIALIZADO | D5: hs | F5: =(50000+12500)/9 -> 6944.4444 | G5: =E5*F5 -> 0 | AI5: 2500 | AJ5: 4 | AK5: =AI5*AJ5 -> 10000 | AM5: 180 | AN5: 4 | AO5: =AN5*AM5*AJ5 -> 2880 | AQ5: =AO5+AK5 -> 12880
B6: Mano de obra | C6: OFICIAL | D6: hs | E6: 1.1 | F6: =(45000+12500)/9 -> 6388.8889 | G6: =E6*F6 -> 7027.7778
B7: Mano de obra | C7: MEDIO OFICIAL | D7: hs | F7: =(40000+12500)/9 -> 5833.3333 | G7: =E7*F7 -> 0 | AK7: =SUM(AK3:AK6) -> 21000 | AO7: =SUM(AO3:AO6) -> 5320 | AQ7: =SUM(AQ3:AQ6) -> 26320 | AR7: =AQ7*50 -> 1316000
B8: Mano de obra | C8: AYUDANTE | D8: hs | E8: 1.05 | F8: =(35000+12500)/9 -> 5277.7778 | G8: =E8*F8 -> 5541.6667
B9: Mano de obra | C9: AYUDA DE GREMIO ayudante | D9: hs | F9: =F8 -> 5277.7778 | G9: =E9*F9 -> 0
B10: SUBTOTAL MANO DE OBRA (A) | G10: =SUM(G5:G9) -> 12569.444 | I10: =G10*K10 -> 117021.53 | K10: =K31 -> 9.31 | T10: =G10 -> 12569.444 | U10: 9.31 | V10: =U10*T10 -> 117021.53
B11: Material | C11: Cemento común (50kg) | D11: kg | E11: =38*0.6 -> 22.8 | F11: =13000/50 -> 260 | G11: =E11*F11 -> 5928
B12: Material | C12: piedra | D12: m3 | E12: =0.08*0.6 -> 0.048 | F12: =250000/5 -> 50000 | G12: =E12*F12 -> 2400
B13: Material | C13: Arena lavada | D13: m3 | E13: =0.08*0.6 -> 0.048 | F13: 50000 | G13: =E13*F13 -> 2400
B14: Material | C14: hierro | D14: kg | E14: 1 | F14: 1800 | G14: =E14*F14 -> 1800 | J14: =0.08*1*1 -> 0.08
B15: Material | C15: Hidrófugo en pasta | D15: kg | E15: 2 | G15: =E15*F15 -> 0 | J15: =J14*6*50 -> 24 | R15: =(G15+G14+G13+G12)*K10 -> 61446
B16: Material | C16: Poliestireno expandido 20 mm | D16: m2 | E16: 1.05 | G16: =E16*F16 -> 0
B17: Material | C17: Polietileno 200 micrones | D17: m2 | E17: 1.05 | G17: =E17*F17 -> 0
B18: Material | G18: =E18*F18 -> 0
B19: Material | G19: =E19*F19 -> 0
B20: Material | G20: =E20*F20 -> 0
B21: Material | G21: =E21*F21 -> 0
B22: Material | G22: =E22*F22 -> 0
B23: Material | G23: =E23*F23 -> 0
B24: Material | G24: =E24*F24 -> 0
B25: SUBTOTAL MATERIAL (B) | G25: =SUM(G11:G24) -> 12528 | Z25: =G25 -> 12528
B27: 1 | C27: MATERIALES | D27: TOTAL (A) | G27: =G10 -> 12569.444
B28: 2 | C28: MANO DE OBRA | D28: TOTAL (B) | G28: =G25 -> 12528
B29: 3 | C29: EQUIPOS | D29: TOTAL (C)
B30: 4 | C30: COSTO - COSTO | D30: (1 + 2 + 3) | G30: =SUM(G27:G29) -> 25097.444
B31: 5 | C31: GASTOS GENERALES | D31: D% x (4) | E31: 0.2 | G31: =+G30*E31 -> 5019.4889 | J31: =G31 -> 5019.4889 | K31: 9.31 | L31: =K31*J31 -> 46731.442 | AA31: =G31 -> 5019.4889
B32: 6 | C32: COSTO - COSTO + GASTOS GENERALES | D32: (4 + 5) | G32: =G31+G30 -> 30116.933
B33: 7 | C33: IMPREVISTOS Y EVENTUALIDADES | D33: E% x (6) | E33: 0.07 | G33: =+G32*E33 -> 2108.1853 | J33: =G33 -> 2108.1853 | K33: 9.31 | M33: =K33*J33 -> 19627.205 | AB33: =G33 -> 2108.1853
B34: 8 | C34: EPP-SEGURIDAD | D34: F% x (6) | E34: 0.02 | G34: =G32*E34 -> 602.33867 | J34: =G34 -> 602.33867 | K34: 9.31 | N34: =K34*J34 -> 5607.773 | AC34: =G34 -> 602.33867
B35: 9 | C35: BENEFICIO | D35: G% x (6) | E35: 0.2 | G35: =G32*E35 -> 6023.3867 | J35: =G35 -> 6023.3867 | K35: 9.31 | O35: =K35*J35 -> 56077.73 | W35: =G35+G34+G33+G31 -> 13753.4 | X35: 9.31 | Y35: =X35*W35 -> 128044.15 | AD35: =G35 -> 6023.3867
B36: 10 | C36: COSTO TOTAL DEL TRABAJO | D36: (6 + 7 + 8 + 9) | G36: =G35+G34+G33+G32 -> 38850.844
B37: 11 | C37: COSTO TOTAL DEL TRABAJO SIN MATERIALES | D37: (10 - 1) | G37: =G36-G28 -> 26322.844
B38: 12 | C38: IMPUESTOS (IIBB - GANANCIAS) | D38: V % x (9) | E38: 0 | G38: =G36*E38 -> 0 | J38: =G38 -> 0 | K38: 9.31 | P38: =K38*J38 -> 0 | AE38: =G38 -> 0
B39: 13 | C39: GANANCIAS | E39: 0 | G39: =G35*E39 -> 0 | J39: =G39 -> 0 | K39: 9.31 | Q39: =K39*J39 -> 0 | AF39: =G39 -> 0
B41: 14 | C41: PRECIO UNITARIO DE APLICACIÓN CON MATERIALES | D41: (10 + 12 + 13) | G41: =G36+G38+G39 -> 38850.844
B42: 15 | C42: PRECIO UNITARIO DE APLICACIÓN CON MATERIALES + IVA | D42: (11 + 12 + 13 + IVA) | G42: =(G36+G38+G39)*1.21 -> 47009.521 | I42: =G27*2 -> 25138.889
B43: 16 | C43: PRECIO UNITARIO DE APLICACIÓN SIN MATERIALES | D43: (10 + 12 + 13) | G43: =G37+G38+G39 -> 26322.844 | I43: =G43/1335 -> 19.717486
B44: 17 | C44: PRECIO UNITARIO DE APLICACIÓN SIN MATERIALES + IVA | D44: (11 + 12 + 13 + IVA) | G44: =(G37+G38+G39)*1.21 -> 31850.641
A46: 1.2 | B46: Partida | C46: COLOCACION DE PISOS | D46: M3
B47: Mano de obra | C47: OFICIAL ESPECIALIZADO | D47: hs | F47: =F5 -> 6944.4444 | G47: =E47*F47 -> 0
B48: Mano de obra | C48: OFICIAL | D48: hs | E48: 0.8 | F48: =F6 -> 6388.8889 | G48: =E48*F48 -> 5111.1111
B49: Mano de obra | C49: MEDIO OFICIAL | D49: hs | F49: =F7 -> 5833.3333 | G49: =E49*F49 -> 0
B50: Mano de obra | C50: AYUDANTE | D50: hs | E50: 0.45 | F50: =F8 -> 5277.7778 | G50: =E50*F50 -> 2375
B51: Mano de obra | C51: AYUDA DE GREMIO ayudante | D51: hs | F51: =F9 -> 5277.7778 | G51: =E51*F51 -> 0
B52: SUBTOTAL MANO DE OBRA (A) | G52: =SUM(G47:G51) -> 7486.1111 | I52: =G52*K52 -> 44168.056 | K52: =K73 -> 5.9 | T52: =G52 -> 7486.1111 | U52: 5.9 | V52: =U52*T52 -> 44168.056
B53: Material | C53: Pastina (1 kg) | D53: kg | E53: 0.4 | F53: 400 | G53: =E53*F53 -> 160
B54: Material | C54: Mezcla adhesiva impermeable para piso (30Kg) | D54: kg | E54: 4 | F54: 90 | G54: =E54*F54 -> 360
B55: Material | C55: Sellador elástico tipo Adhesil 65 | D55: m | E55: 0.5 | F55: 200 | G55: =E55*F55 -> 100
B56: Material | C56: Piso porcellanato 50 x 50 antideslizante | D56: m2 | E56: 1.05 | F56: 1200 | G56: =E56*F56 -> 1260
B57: Material | G57: =E57*F57 -> 0 | R57: =(G57+G56+G55+G54)*K52 -> 10148
B58: Material | G58: =E58*F58 -> 0
B59: Material | G59: =E59*F59 -> 0
B60: Material | G60: =E60*F60 -> 0
B61: Material | G61: =E61*F61 -> 0
B62: Material | G62: =E62*F62 -> 0
B63: Material | G63: =E63*F63 -> 0
B64: Material
B65: Material
B66: Material
B67: SUBTOTAL MATERIAL (B) | G67: =SUM(G53:G66) -> 1880 | Z67: =G67 -> 1880
B69: 1 | C69: MATERIALES | D69: TOTAL (A) | G69: =G52 -> 7486.1111
B70: 2 | C70: MANO DE OBRA | D70: TOTAL (B) | G70: =G67 -> 1880
B71: 3 | C71: EQUIPOS | D71: TOTAL (C)
B72: 4 | C72: COSTO - COSTO | D72: (1 + 2 + 3) | G72: =SUM(G69:G71) -> 9366.1111
B73: 5 | C73: GASTOS GENERALES | D73: D% x (4) | E73: 0.12 | G73: =+G72*E73 -> 1123.9333 | J73: =G73 -> 1123.9333 | K73: 5.9 | L73: =K73*J73 -> 6631.2067 | AA73: =G73 -> 1123.9333
B74: 6 | C74: COSTO - COSTO + GASTOS GENERALES | D74: (4 + 5) | G74: =G73+G72 -> 10490.044
B75: 7 | C75: IMPREVISTOS Y EVENTUALIDADES | D75: E% x (6) | E75: 0.08 | G75: =+G74*E75 -> 839.20356 | J75: =G75 -> 839.20356 | K75: 5.9 | M75: =K75*J75 -> 4951.301 | AB75: =G75 -> 839.20356
B76: 8 | C76: EPP-SEGURIDAD | D76: F% x (6) | E76: 0.05 | G76: =G74*E76 -> 524.50222 | J76: =G76 -> 524.50222 | K76: 5.9 | N76: =K76*J76 -> 3094.5631 | AC76: =G76 -> 524.50222
B77: 9 | C77: BENEFICIO | D77: G% x (6) | E77: 0.15 | G77: =G74*E77 -> 1573.5067 | J77: =G77 -> 1573.5067 | K77: 5.9 | O77: =K77*J77 -> 9283.6893 | W77: =G77+G76+G75+G73 -> 4061.1458 | X77: 5.9 | Y77: =X77*W77 -> 23960.76 | AD77: =G77 -> 1573.5067
B78: 10 | C78: COSTO TOTAL DEL TRABAJO | D78: (6 + 7 + 8 + 9) | G78: =G77+G76+G75+G74 -> 13427.257
B79: 11 | C79: COSTO TOTAL DEL TRABAJO SIN MATERIALES | D79: (10 - 1) | G79: =G78-G70 -> 11547.257
B80: 12 | C80: IMPUESTOS (IIBB - GANANCIAS) | D80: V % x (9) | E80: 0.03 | G80: =G78*E80 -> 402.81771 | J80: =G80 -> 402.81771 | K80: 5.9 | P80: =K80*J80 -> 2376.6245 | AE80: =G80 -> 402.81771
B81: 13 | C81: GANANCIAS | E81: 0.35 | G81: =G77*E81 -> 550.72733 | J81: =G81 -> 550.72733 | K81: 5.9 | Q81: =K81*J81 -> 3249.2913 | AF81: =G81 -> 550.72733
B83: 14 | C83: PRECIO UNITARIO DE APLICACIÓN CON MATERIALES | D83: (10 + 12 + 13) | G83: =G78+G80+G81 -> 14380.802
B84: 15 | C84: PRECIO UNITARIO DE APLICACIÓN CON MATERIALES + IVA | D84: (11 + 12 + 13 + IVA) | G84: =(G78+G80+G81)*1.21 -> 17400.77
B85: 16 | C85: PRECIO UNITARIO DE APLICACIÓN SIN MATERIALES | D85: (10 + 12 + 13) | G85: =G79+G80+G81 -> 12500.802 | I85: =G83*0.6 -> 8628.4812
B86: 17 | C86: PRECIO UNITARIO DE APLICACIÓN SIN MATERIALES + IVA | D86: (11 + 12 + 13 + IVA) | G86: =(G79+G80+G81)*1.21 -> 15125.97
A91: 5.2 | B91: Partida | C91: muros de contencion bloque hormigon | D91: m2
B92: Mano de obra | C92: AYUDANTE | D92: h | E92: 0.7 | F92: =F69 -> 0 | G92: =E92*F92 -> 0
B93: Mano de obra | C93: OFICIAL | D93: h | E93: 0.75 | F93: =F42 -> 0 | G93: =E93*F93 -> 0
B94: Mano de obra | C94: ayuda gremio | D94: h | F94: =F43 -> 0
B95: SUBTOTAL MANO DE OBRA (B) | G95: =SUM(G92:G94) -> 0
B96: Material | C96: Cemento (bolsa x 50 kg) | D96: kg | E96: 3.09 | F96: 26 | G96: =E96*F96 -> 80.34
B97: Material | C97: Arena común | D97: m3 | E97: 0.03 | F97: 3500 | G97: =E97*F97 -> 105
B98: Material | C98: Hierro redondo estriado 12/500-528 | D98: kg | E98: 4 | F98: 216 | G98: =E98*F98 -> 864
B99: Material | C99: bloques de hormigon 20/20/40 | D99: u | E99: 12.5 | F99: 200 | G99: =E99*F99 -> 2500
B100: SUBTOTAL MATERIAL (A) | G100: =SUM(G96:G99) -> 3549.34
A104: 1.2 | B104: Partida | C104: Muros bloques de cemento 40/40 | D104: M3
B105: Mano de obra | C105: OFICIAL ESPECIALIZADO | D105: hs | F105: =F47 -> 6944.4444 | G105: =E105*F105 -> 0
B106: Mano de obra | C106: OFICIAL | D106: hs | E106: 0.75 | F106: =F48 -> 6388.8889 | G106: =E106*F106 -> 4791.6667
B107: Mano de obra | C107: MEDIO OFICIAL | D107: hs | F107: =F49 -> 5833.3333 | G107: =E107*F107 -> 0
B108: Mano de obra | C108: AYUDANTE | D108: hs | E108: 0.7 | F108: =F50 -> 5277.7778 | G108: =E108*F108 -> 3694.4444
B109: Mano de obra | C109: AYUDA DE GREMIO ayudante | D109: hs | F109: =F51 -> 5277.7778 | G109: =E109*F109 -> 0 | I109: 110
B110: SUBTOTAL MANO DE OBRA (A) | G110: =SUM(G105:G109) -> 8486.1111 | K110: =K131 -> 5.9 | T110: =G110 -> 8486.1111 | U110: 5.9 | V110: =U110*T110 -> 50068.056
B111: Material | C111: Cemento (bolsa x 50 kg) | D111: kg | E111: 3.09 | F111: =13000/50 -> 260 | G111: =E111*F111 -> 803.4 | I111: =E111*J111/50 -> 6.798 | J111: 110
B112: Material | C112: Arena común | D112: m3 | E112: 0.03 | F112: =250000/5 -> 50000 | G112: =E112*F112 -> 1500 | I112: =E112*J112 -> 3.3 | J112: 110
...

Sheet Hoja5
I5: EN DOLARES
B6: 7500 | C6: 4 | D6: =B6*C6 -> 30000 | E6: 1 | F6: 350000 | G6: =F6*E6 -> 350000 | I6: =B6/289 -> 25.951557 | J6: 4 | K6: =J6*I6 -> 103.80623 | L6: 1 | M6: =F6/289 -> 1211.0727 | N6: =M6*L6 -> 1211.0727 | O6: maquina
B7: 8000 | C7: 3 | D7: =B7*C7 -> 24000 | E7: 1 | F7: 70000 | G7: =F7*E7 -> 70000 | I7: =B7/289 -> 27.681661 | J7: 3 | K7: =J7*I7 -> 83.044983 | L7: 1 | M7: =70000/289 -> 242.21453 | N7: =M7*L7 -> 242.21453 | O7: camion
B8: 4300 | C8: 75 | D8: =B8*C8 -> 322500 | E8: 1.75 | F8: =E8*B8 -> 7525 | G8: =F8*C8 -> 564375 | I8: =B8/289 -> 14.878893 | J8: 75 | K8: =J8*I8 -> 1115.917 | L8: 1.7 | M8: =L8*I8 -> 25.294118 | N8: =M8*J8 -> 1897.0588 | O8: cerco
B9: 785 | C9: 78 | D9: =B9*C9 -> 61230 | E9: =E8 -> 1.75 | F9: =E9*B9 -> 1373.75 | G9: =F9*C9 -> 107152.5 | I9: =B9/289 -> 2.716263 | J9: 203 | K9: =J9*I9 -> 551.40138 | L9: =L8 -> 1.7 | M9: =L9*I9 -> 4.6176471 | N9: =M9*J9 -> 937.38235 | O9: replanteo | P9: =N9*306 -> 286839
B10: 5130 | C10: 3 | D10: =B10*C10 -> 15390 | E10: =E9 -> 1.75 | F10: =E10*B10 -> 8977.5 | G10: =F10*C10 -> 26932.5 | I10: =B10/289 -> 17.750865 | J10: 3 | K10: =J10*I10 -> 53.252595 | L10: =L9 -> 1.7 | M10: =L10*I10 -> 30.176471 | N10: =M10*J10 -> 90.529412 | O10: excavacion manual
B11: 5137 | C11: 1.7 | D11: =B11*C11 -> 8732.9 | E11: =E10 -> 1.75 | F11: =E11*B11 -> 8989.75 | G11: =F11*C11 -> 15282.575 | I11: =B11/289 -> 17.775087 | J11: 1.7 | K11: =J11*I11 -> 30.217647 | L11: =L10 -> 1.7 | M11: =L11*I11 -> 30.217647 | N11: =M11*J11 -> 51.37 | O11: excavacion manual
B12: 3960 | C12: 110 | D12: =B12*C12 -> 435600 | E12: =E11 -> 1.75 | F12: =E12*B12 -> 6930 | G12: =F12*C12 -> 762300 | I12: =B12/289 -> 13.702422 | J12: 110 | K12: =J12*I12 -> 1507.2664 | L12: =L11 -> 1.7 | M12: =L12*I12 -> 23.294118 | N12: =M12*J12 -> 2562.3529 | O12: mamposteria
B13: 3460 | C13: 51.1 | D13: =B13*C13 -> 176806 | E13: =E12 -> 1.75 | F13: =E13*B13 -> 6055 | G13: =F13*C13 -> 309410.5 | I13: =B13/289 -> 11.972318 | J13: 51.1 | K13: =J13*I13 -> 611.78547 | L13: =L12 -> 1.7 | M13: =L13*I13 -> 20.352941 | N13: =M13*J13 -> 1040.0353 | O13: encadenados
B14: 4660 | C14: 40.5 | D14: =B14*C14 -> 188730 | E14: =E13 -> 1.75 | F14: =E14*B14 -> 8155 | G14: =F14*C14 -> 330277.5 | I14: =B14/289 -> 16.124567 | J14: 40.5 | K14: =J14*I14 -> 653.04498 | L14: =L13 -> 1.7 | M14: =L14*I14 -> 27.411765 | N14: =M14*J14 -> 1110.1765 | O14: columnas
B15: 7850 | C15: 45 | D15: =B15*C15 -> 353250 | E15: =E14 -> 1.75 | F15: =E15*B15 -> 13737.5 | G15: =F15*C15 -> 618187.5 | I15: =B15/289 -> 27.16263 | J15: 45 | K15: =J15*I15 -> 1222.3183 | L15: =L14 -> 1.7 | M15: =L15*I15 -> 46.176471 | N15: =M15*J15 -> 2077.9412 | O15: plateas
B16: 650 | C16: 90 | D16: =B16*C16 -> 58500 | E16: =E15 -> 1.75 | F16: =E16*B16 -> 1137.5 | G16: =F16*C16 -> 102375 | I16: =B16/289 -> 2.2491349 | J16: 90 | K16: =J16*I16 -> 202.42215 | L16: =L15 -> 1.7 | M16: =L16*I16 -> 3.8235294 | N16: =M16*J16 -> 344.11765 | O16: azotado
B17: 2930 | C17: 60 | D17: =B17*C17 -> 175800 | E17: =E16 -> 1.75 | F17: =E17*B17 -> 5127.5 | G17: =F17*C17 -> 307650 | I17: =B17/289 -> 10.138408 | J17: 60 | K17: =J17*I17 -> 608.3045 | L17: =L16 -> 1.7 | M17: =L17*I17 -> 17.235294 | N17: =M17*J17 -> 1034.1176 | O17: membranas
B18: 6300 | C18: 30 | D18: =B18*C18 -> 189000 | E18: =E17 -> 1.75 | F18: =E18*B18 -> 11025 | G18: =F18*C18 -> 330750 | I18: =B18/289 -> 21.799308 | J18: 30 | K18: =J18*I18 -> 653.97924 | L18: =L17 -> 1.7 | M18: =L18*I18 -> 37.058824 | N18: =M18*J18 -> 1111.7647 | O18: viguetas
D20: =SUM(D6:D19) -> 2039538.9 | G20: =SUM(G6:G19) -> 3894693.1 | K20: =SUM(K6:K19) -> 7396.7609 | N20: =SUM(N6:N19) -> 13710.134
M22: =N20-K20 -> 6313.3728

Sheet Hoja1
A1: estructura sobre planta baja | E1: peso | I1: metro cuadrado de pared planta alta
A2: vigas | D2: m/l | P2: PRECIO APROX
A3: 2 | B3: 140 | C3: 7 | D3: =C3*A3 -> 14 | E3: 4.51 | F3: =E3*D3 -> 63.14 | I3: pgc 100 | J3: 6290 | K3: =J3*1.2 -> 7548 | N3: PAREDES EXTERIORES: PGC 100; PGU 100; PLACAS OSB 11mm (dobles); TYBEK; PLACA YESO 12,5mm; CELULOSA 100mm; TORNILLERIAS | P3: =K3+K4+K7+K8+K9+K12+K15 -> 28916.556
A4: 4 | B4: 140 | C4: 6.9 | D4: =C4*A4 -> 27.6 | E4: 4.51 | F4: =E4*D4 -> 124.476 | I4: pgu 100 | J4: 1590 | K4: =J4*1.2 -> 1908
A5: 4 | B5: 140 | C5: 2.6 | D5: =C5*A5 -> 10.4 | E5: 4.51 | F5: =E5*D5 -> 46.904 | I5: mont 70 | J5: 897.82 | K5: =J5*1.2 -> 1077.384
A6: 2 | B6: 140 | C6: 4.5 | D6: =C6*A6 -> 9 | E6: 4.51 | F6: =E6*D6 -> 40.59 | I6: solera 70 | J6: 401.5 | K6: =J6*1.2 -> 481.8
A7: 2 | B7: 140 | C7: 8.3 | D7: =C7*A7 -> 16.6 | E7: 4.51 | F7: =E7*D7 -> 74.866 | I7: placa osb | J7: 5623.13 | K7: =J7*1.2 -> 6747.756
I8: placa yeso | J8: 1840 | K8: =J8*1.2 -> 2208
A9: 2 | B9: 200 | C9: 4.5 | D9: =C9*A9 -> 9 | E9: 7.72 | F9: =E9*D9 -> 69.48 | I9: tybek | J9: 254 | K9: =J9*1.2 -> 304.8 | N9: PAREDES INTERIORES: PGC 100; PGU 100; PLACAS OSB 11mm (dobles); PLACA YESO 12,5mm (dobles); CELULOSA 100mm; TORNILLERIAS | P9: =+K3+K4+K7+K8+K12+J15 -> 27611.756
A10: 3 | B10: 200 | C10: 4.4 | D10: =C10*A10 -> 13.2 | E10: 7.72 | F10: =E10*D10 -> 101.904 | I10: eps 50 | J10: 3590 | K10: =J10*1.2 -> 4308
I11: alf 2"x2" | J11: 795 | K11: =J11*1.2 -> 954
A12: columnas | I12: celulosa 100 | J12: 3500 | K12: =J12*1.2 -> 4200
A13: 7 | B13: 200 | C13: 2.5 | D13: =C13*A13 -> 17.5 | E13: 7.72 | F13: =E13*D13 -> 135.1 | I13: chapa | J13: 5470 | K13: =J13*1.2 -> 6564
A14: 18 | B14: 140 | C14: 2.5 | D14: =C14*A14 -> 45 | E14: 4.51 | F14: =E14*D14 -> 202.95 | J14: =SUM(J3:J13) -> 30251.45 | K14: m2 | L14: =J12+J9+J8+J7+J6+J5+J4+J3 -> 20396.45
I15: tornilleria | J15: 5000 | K15: =J15*1.2 -> 6000 | N15: REVESTIMIENTOS EXTERIORES: EPS 50mm; ALFAJIAS 2"X2"; CHAPA SINUSOIDAL; TORNILLERIAS | P15: =+K11+K10+K13+J15-1500 -> 15326
A16: plancuelas de 1/4" | J16: =SUM(J14:J15) -> 35251.45 | K16: =SUM(K3:K4,K7,K8,K9,K11,K12,K13,K15) -> 36434.556
C17: m2 | D17: m2
A18: 12 | C18: =(0.3*0.3)+(0.1*0.2) -> 0.11 | D18: =C18*A18 -> 1.32 | E18: 49.85 | F18: =E18*D18 -> 65.802 | I18: =J18*1.25 -> 27821.413 | J18: =J3+J4+J7+J9+J12+J15 -> 22257.13 | L18: 2851400.4
J19: 310.55 | L19: 2356629.3
A20: estructura sobre planta alta | J20: =J19*J18 -> 6911951.7 | L20: =L18-L19 -> 494771.14
A21: vigas | L21: =L20/2 -> 247385.57 | M21: =L18-L21 -> 2604014.8 | N21: =M21/393 -> 6625.9919
A22: 1 | B22: 160 | C22: 22.15 | D22: =C22*A22 -> 22.15 | E22: 4.82 | F22: =E22*D22 -> 106.763 | M22: 450000 | N22: maquina
M23: 150000 | N23: postes y alambrados
M24: 189000 | N24: losetas
A25: columnas | M25: 26988 | N25: replanteos
M26: 15390 | N26: excavacion manual vigas
A27: 5 | B27: 160 | C27: 2.3 | D27: =C27*A27 -> 11.5 | E27: 4.82 | F27: =E27*D27 -> 55.43 | M27: 10274 | N27: excavacion manual bases
M28: 435000 | N28: mamposteria
A29: plancuelas de 3/16" | M29: 136000 | N29: vigas 20/40
C30: m2 o m/l | M30: 183726 | N30: encadenados
A31: 7 | C31: =0.2*0.2 -> 0.04 | D31: =C31*A31 -> 0.28 | E31: 37.7 | F31: =E31*D31 -> 10.556 | M31: 137700 | N31: columnas
A32: 7 | C32: 1.6 | D32: =C32*A32 -> 11.2 | E32: 0.888 | F32: =E32*D32 -> 9.9456 | M32: 56250 | N32: cerecita
F33: =SUM(F22:F32) -> 182.6946 | H33: 1.95 | J33: =H33*F33 -> 356.25447 | K33: =J33*180 -> 64125.805 | M33: 205100 | N33: membrana
M34: 432000 | N34: plateas
L35: TOTAL | M35: =SUM(M22:M34) -> 2427428 | N35: 290 | O35: =M35/N35 -> 8370.4414
A36: cabriada de madera | M36: =M35*1.8 -> 4369370.4 | O36: =O35/78 -> 107.31335
F38: 58500 | M38: =M36-M35 -> 1941942.4
K39: =F38+K33 -> 122625.8

Sheet COMPUTO
A1: GONZALEZ GABRIEL ALEJANDRO - M.M.O. MAT: B1-1683/3 - LOSA SEBASTIAN - ARQ. MAT: 2066/3
A2: San Carlos de Bariloche, 22 de Noviembre de 2022
A3: De nuestra mayor consideración: Tenemos el agrado de elevar para vuestra consideración la siguiente Cotización sobre: Construcción Vivienda Unifamiliar - BARRANCAS DE DINA HUAPI - LOTE 350
A4: Provisión de toda la mano de obra necesaria para la completa construcción y culminación de trabajos estructurales de Hormigon Armado; Bases, Troncos de columnas, Vigas de Fundaciones, Plateas de Fundaciones, Columnas S/PB, Vigas S/PB, Losa S/PB, columnas S/PA, Vigas S/PA, Losa S/PA, según lineamientos de la documentación entregadas por Ustedes.
A5: Monto Total de la Obra expresada en pesos: ..................................................... | F5: =F60 -> #REF! | I5: =F60 -> #REF! | J5: =I5/110/80 -> #REF!
B6: SON PESOS NOVECIENTOS OCHENTA Y SIETE MIL NOVECIENTOS TREINTA Y SIETE CON 19/100 | I6: =F68 -> #REF!
A7: Valor expreado en dolares blue. - Consideraciones Generales Otros detalles no especificados en la documentación y que fuera objeto de análisis para el cálculo de la presente cotización, a definir y cotizar. - Obras a desarrollarse en Días hábiles APTOS: se consideran días de ejecución semanal en horario de 9hs. a 17hs. (a criterio técnico de nuestro personal, a coordinar), en condiciones normales de trabajo SEGURO a la Intemperie; otras “a nuestro exclusivo criterio”. - Todos los servicios necesarios para la realización de las obras en el sector OBRA (agua, electricidad, sanitarios), se consideran provistos por el cliente a pie de obra. - Nuestro personal calificado (por rubros) prestara sus servicios en obra, con máquinas y herramientas, EPP e infraestructura apta para las distintas tareas a realizar, a nuestro criterio.
A8: En la presente cotización no se incluyen: • Movimientos de suelos a Maquina. • Aportes de suelos. • Materiales. • Insumibles. • Maderas para encofrados.
A9: ITEM | B9: DESCRIPCION | C9: UND. | D9: CANT. | E9: P. UNITARIO | F9: P. TOTAL ITEM
A10: 1 - TAREAS PRELIMINARES
A11: 1.1 | B11: Replanteo | C11: Gl. | D11: 1 | E11: =Hoja5!N9*306 -> 286839 | F11: =E11*D11 -> 286839 | G11: 318 | H11: =F11/G11 -> 902.00943
A12: 1.2 | B12: Obrador y Baño quimico | C12: MES | D12: 3 | E12: =(22000*1+15000) -> 37000 | F12: =E12*D12+(65000/308) -> 111211.04 | G12: =G11 -> 318 | H12: =F12*G12 -> 35365110
A13: 1.3 | B13: Cerco de obra (NO SE COTIZA) | G13: =G12 -> 318
D14: SUBTOTAL ITEM 1.- | F14: =SUM(F11:F13) -> 398050.04 | G14: =G13 -> 318 | I14: =F14 -> 398050.04
A15: 2 - EXCAVACIONES, HORMIGON FUNDACIONES, PLATEAS, COLUMNAS Y VIGAS. | G15: =G14 -> 318
A16: 2.1 | B16: Movimientos de suelos y excavaciones manuales para bases y vigas. Relleno y compactación de suelos seleccionados | C16: Gl. | D16: 1 | E16: =Hoja6!K78 -> 148.25135 | F16: =E16*D16 -> 148.25135 | G16: =G15 -> 318 | H16: =F16*G16 -> 47143.93 | I16: =F16*0.8 -> 118.60108
A17: 2.2 | B17: Bases aisladas de fundacion | C17: M3 | D17: =Hoja6!J195 -> 1200 | E17: =Hoja6!G195 -> 572583.68 | F17: =E17*D17 -> 6.8710042e+08 | G17: =G16 -> 318 | H17: =F17*G17 -> 2.1849793e+11
A18: 2.3 | B18: Troncos de Columnas | C18: M3 | D18: =Hoja6!J234 -> 1200 | E18: =Hoja6!G234 -> 658367.02 | F18: =E18*D18 -> 7.9004043e+08 | G18: =G17 -> 318 | H18: =F18*G18 -> 2.5123286e+11
A19: 2.4 | B19: Vigas, Contrapisos y Losas de fundaciones niveles -0,10 y -0,20 | C19: M3 | D19: 31.02 | E19: =Hoja6!#REF!*305 -> #REF! | F19: =E19*D19 -> #REF! | G19: =G18 -> 318 | H19: =F19*G19 -> #REF! | I19: =F19/203 -> #REF!
A20: 2.5 | B20: Columnas y C/E sobre Planta Baja y Alta | C20: M3 | D20: =Hoja6!J273 -> 1200 | E20: =Hoja6!G273 -> 658367.02 | F20: =E20*D20 -> 7.9004043e+08 | G20: =G19 -> 318 | H20: =F20*G20 -> 2.5123286e+11
A21: 2.6 | B21: Vigas y encadenados | C21: M3 | D21: =Hoja6!J312 -> 1200 | E21: =Hoja6!G312 -> 1597659.4 | F21: =E21*D21 -> 1.9171913e+09 | G21: =G20 -> 318 | H21: =F21*G21 -> 6.0966683e+11
A22: 2.7 | B22: Losas sobre Planta Baja y Alta | C22: M3 | D22: =Hoja6!J351 -> 1200 | E22: =Hoja6!G351 -> 1112884.3 | F22: =E22*D22 -> 1.3354612e+09 | G22: =G21 -> 318 | H22: =F22*G22 -> 4.2467666e+11
D23: SUBTOTAL ITEM 2.- | F23: =SUM(F16:F22) -> #REF! | I23: =SUM(H16:H17) -> 2.1849798e+11
A24: 3 - MAMPOSTERIAS, REVOQUES Y DRENAJES
A25: 3.1 | B25: Muros de contencion en bloques hormigon armado, azotados hidrofugos verticales, pintura con emulsion asfaltica, colocacion de membrana asfaltica, aislaciones de EPS y drenajes perimetrales. | C25: Gl. | E25: =Hoja5!N12+Hoja5!N16+Hoja5!N17+650 -> 4590.5882 | F25: =E25*D25 -> 0
D26: SUBTOTAL ITEM 3.- | F26: =SUM(F25) -> 0 | H26: =F26+F23+F14 -> #REF!
A27: 4 - ESTRUCTURA STEEL FRAMING
A28: 4.1 | B28: PARED EXTERIOR Panel Steel Framing, compuesta por: Membrana Hydrofuga, Placa OSB 11,1, Perfil CSH PGC 100x40x0,9, Celulosa Pro, Placa OSB 11,1 | C28: m2 | E28: =7298/204 -> 35.77451 | F28: =E28*D28 -> 0 | I28: =F28 -> 0
A29: 4.2 | B29: PARED INTERIOR Panel Steel Framing, compuesta por: Placa OSB 11,1, Perfil CSH PGC 100x40x0,9, Celulosa Pro, Placa OSB 11,1 | C29: m2 | E29: =6060/204 -> 29.705882 | F29: =E29*D29 -> 0 | I29: =F29 -> 0
A30: 4.3 | B30: ENTREPISO Panel Steel Framing, compuesta por: Fenolico 18mm, Perfil CSH PGC 100x40x0,9, Lana de vidrio PV 100 c/aluminio | C30: m2 | E30: =7203/204 -> 35.308824 | F30: =E30*D30 -> 0
A31: 4.4 | B31: Armado de techo en madera con cabios, machimbre aislacion clavaderas y chapa , Panel MegaSytem C Foil/Prepintado-50 | C31: m2 | E31: =12030/308 -> 39.058442 | F31: =E31*D31 -> 0 | H31: =E31/106.34 -> 0.36729774
D32: SUBTOTAL ITEM 4.- | F32: =SUM(F28:F31) -> 0
A33: 5 - REVESTIMIENTOS
A34: 5.1 | B34: Revestimiento pared interior con placa de yeso de 12,5 encintado y masillado (no incluye lijado) | C34: m2 | E34: =3500/308 -> 11.363636 | F34: =E34*D34 -> 0
A35: 5.2 | B35: Revestimiento cielorraso interior PB y sanitarios PA, con placa de yeso de 12,5 encintado y masillado (no incluye lijado) | C35: m2 | E35: =E34 -> 11.363636 | F35: =E35*D35 -> 0
A36: 5.3 | B36: Revestimiento exterior EIFS con terminacion base coat o siding | C36: m2 | E36: =3920/308 -> 12.727273 | F36: =E36*D36 -> 0
A37: 5.3 | B37: Revestimiento tipo revear | C37: m2 | E37: =2900/308 -> 9.4155844 | F37: =E37*D37 -> 0
A38: 5.3 | B38: Colocacion de chapa en paredes exteriores | C38: m2 | E38: =2920/308 -> 9.4805195 | F38: =E38*D38 -> 0
D39: SUBTOTAL ITEM 5.- | F39: =SUM(F34:F38) -> 0 | I39: =F39 -> 0
A40: 5 - PISOS, CONTRAPISOS
A41: 5.1 | B41: Contrapiso de Nivelación 8cm | C41: m2 | E41: =6800/308 -> 22.077922 | F41: =E41*D41 -> 0
A42: 5.2 | B42: Colocacion Pisos (no se cotizan)
A43: 5.3 | B43: Colocacion zocalos madera (no se cotizan)
D44: SUBTOTAL ITEM 5.- | F44: =SUM(F41:F43) -> 0
A45: 6 - INSTALACIONES
A46: 6.1 | B46: Instalacion de Gas y tramite ante Camuzzi | C46: Gl. | E46: =25000*9/204 -> 1102.9412 | F46: =E46*D46 -> 0
A47: 6.2 | B47: Instalacion agua fria y caliente | C47: Gl. | E47: =14*20000/204 -> 1372.549 | F47: =E47*D47 -> 0
A48: 6.3 | B48: Instalacion electrica completa | C48: Gl. | E48: =772500/308 -> 2508.1169 | F48: =E48*D48 -> 0
A49: 6.4 | B49: Instalacion calefaccion por piso radiante | C49: Gl. | E49: =620000/308 -> 2012.987 | F49: =E49*D49 -> 0
D50: SUBTOTAL ITEM 5.- | F50: =SUM(F46:F48) -> 0
A51: 7 - PINTURA (no se incluyen los materiales)
A52: 7.1 | B52: Pintura al latex paredes interiores | C52: m2 | E52: =3820/308 -> 12.402597 | F52: =E52*D52 -> 0
A53: 7.2 | B53: Pintura al latex cielorrasos interiores | C53: m2 | E53: =3820/308 -> 12.402597 | F53: =E53*D53 -> 0
A54: 5.4 | B54: Pintura sobre madera techo | C54: m2 | E54: =3500/308 -> 11.363636 | F54: =E54*D54 -> 0
D55: SUBTOTAL ITEM 7.- | F55: =SUM(F52:F54) -> 0
A56: 6 - VARIOS
A57: 6.1 | B57: Limpieza periódica y final de obra | C57: Gl. | E57: =(6*22.5*0.4*6500)/308 -> 1139.6104 | F57: =E57*D57 -> 0 | H57: =E57/308 -> 3.7000337
D58: SUBTOTAL ITEM 6.- | F58: =SUM(F57:F57) -> 0 | I58: =F60/110 -> #REF! | J58: =I58/80.37 -> #REF!
A60: TOTAL PRESUPUESTO | F60: =SUM(F23+F14) -> #REF! | G60: =G16 -> 318 | H60: =SUM(H11:H23) -> #REF! | I60: =F60*0.06 -> #REF! | J60: =F60/H60 -> #REF!
A62: En la presente cotizacion no se incluyen valores de IVA.
A63: Los valores expresados en la presente cotizacion, de mano de obra, estan expresados en dólares | H63: =F60/309.24 -> #REF! | I63: =H63/112 -> #REF!
A64: La presente cotización tiene validez por 30 días.
A65: Forma de pago: 15% de anticipo y certificaciones quincenales según avance de obra.
A67: Valor m2 de esta construccion | E67: Por Mano de Obra | F67: =F60 -> #REF!
A68: Valor U$S oficial al 08/11/21 = | C68: 203 | F68: =F67/C68 -> #REF! | H68: 51446.32 | I68: =SUM(I13:I58) -> #REF! | J68: =I68/160 -> #REF! | K68: =J68/196 -> #REF!
F70: 116697.23 | I70: =I68*3 -> #REF! | J70: =I70/160 -> #REF! | K70: =J70/196 -> #REF!
A71: FRAGMENTO TEXTO CONVENIO COLECTIVO UOCRA "1.- Establecer un incremento salarial complementario y adicional al previsto en el acuerdo de fecha 9 de Abril de 2021 que se ratifica íntegramente y que se aplicará respecto de las distintas categorías previstas en los Convenios Colectivos de Trabajo N° 76/75 y 577/10 de la siguiente manera: Los porcentajes adicionales, aplicados sobre los salarios básicos vigentes al 31 de marzo de 2021, serán: a) 5% (cinco por ciento) a partir del mes de Septiembre de 2021; b) 5% (cinco por ciento) a partir del mes de enero de 2022 c) 2% a partir del mes de Marzo de 2022, que se aplicará sobre los salarios básicos vigentes al 31 de marzo de 2021. En virtud de ello, el cronograma y los porcentuales correspondiente al periodo Julio 2021 a Marzo 2022 ambos inclusive, quedará compuesto e integrado de siguiente manera, todos aplicados sobre los salarios básicos al 31 de marzo de 2021: a) Un aumento a partir del mes de Julio de 2021 del 22% (veintidós por ciento); b) Un aumento a partir del mes de Septiembre de 2021 del 27% (veintisiete por ciento): c) Un aumento a partir del mes de Octubre de 2021 del 34 % (treinta y cuatro por ciento); d) Un aumento a partir del mes de Enero de 2022 del 39 % (treinta y nueve por ciento) e) Un aumento a partir del mes de Febrero de 2022 del 45,8% (durante y cinco coma ocho por ciento); f) Un aumento a partir del mes de Marzo de 2022 del 47,8% (cuarenta y siete coma ocho por ciento)."

Sheet gastos
A2: concepto | B2: fecha | C2: monto
A3: copias de planos | B3: 44942 | C3: 4073
A4: Nylon ferreteria y candado | B4: 44958 | C4: 10600
A5: cemento loma negra | B5: 44971 | C5: 13750
A6: combustible grupo elect. | B6: 44971 | C6: 1400
A7: termomagnetica y riel din centro electrico | B7: 44971 | C7: 4141.44
A8: 1 dia de alquiler grupo en alquilotodo | B8: 44974 | C8: 6000
A9: combustible grupo elect. | B9: 44979 | C9: 3000
A10: 2 kilos de clavo 1/2" | B10: 44985 | C10: 1900
A11: 2 kilos de clavo 1/2" | B11: 44999 | C11: 4750
C16: =SUM(C3:C15) -> 49614.44

Sheet Hoja3
E2: m3 | F2: 18.5
E3: m2 | F3: 119.3
E5: maquinaria 1 dia de trabajo, extraccion de material vegetal | F5: 50000
E6: mano de obra exc | F6: 0
E7: mano de obra compactado | F7: =(7000+5000)*5 -> 60000
A8: mano de obra x m2 | C8: =F8/F3 -> 3300 | E8: mano de obra H°A° | F8: =F3*3300 -> 393690 | I8: 6 | J8: 8 | K8: 10
A9: mano de obra x m3 | C9: =F8/F2 -> 21280.541 | E9: materiales H°A° | F9: =SUM(L14:L22) -> 494413.64 | I9: =209.47/12 -> 17.455833 | J9: =2110.66/12 -> 175.88833 | K9: =24.82/12 -> 2.0683333
E10: total costo-costo | F10: =SUM(F8:F9) -> 888103.64 | I10: 633 | J10: 1100.5 | K10: 1719
E12: 15% gastos generales | F12: =F10*0.15 -> 133215.55
F13: =F12+F10 -> 1021319.2
C14: =F14+F12 -> 439611.3 | E14: 15% de beneficio + 10% de imprevistos + 3% eventualidades + 1% de seguridad (29%) | F14: =F13*0.3 -> 306395.76 | H14: hierro | I14: =I10*I9 -> 11049.543 | J14: =J10*J9 -> 193565.11 | K14: =K10*K9 -> 3555.465 | L14: =SUM(I14:K14) -> 208170.12
F15: =F13+F14 -> 1327714.9 | G15: =F10*1.45 -> 1287750.3
E19: 3% ingresos brutos | F19: =F15*0.03 -> 39831.448 | H19: barras | J19: 14000 | K19: 18.5 | L19: =K19*J19 -> 259000
E20: 35% ganancias | F20: =F14*0.35 -> 107238.51 | H20: alambre | J20: 368 | K20: 10 | L20: =K20*J20 -> 3680
B21: costo m2 | C21: =F22/F2 -> 79718.103 | H21: clavos | J21: 544 | K21: 10 | L21: =K21*J21 -> 5440
E22: total sin IVA | F22: =F20+F19+F15 -> 1474784.9 | H22: madera | I22: 33.3 | J22: 0.35 | K22: 1555 | L22: =K22*J22*I22 -> 18123.525
B23: costo m3 | C23: =F22/F3 -> 12361.986
E24: TOTAL SIN MATERIALES Y SIN IVA | F24: =F28+F19+F20 -> 980371.27
F26: =F24-F20-F19 -> 833301.3 | H26: =F26/119.3 -> 6984.9229
A28: costo m2 sin materiales | C28: =F28/F3 -> 6984.9229 | E28: SUBTOTAL SIN MATERIALES | F28: =F15-F9 -> 833301.3
A29: costo m2 sin materiales | C29: =F28/F2 -> 45043.314 | G29: =F28-F8 -> 439611.3

Sheet Hoja7
A1: 1.2 | B1: Partida | C1: PAVIMENTOS | D1: M2
B2: Mano de obra | C2: OFICIAL ESPECIALIZADO | D2: hs | E2: 0 | F2: =80000/8+5789 -> 15789 | G2: =E2*F2 -> 0
B3: Mano de obra | C3: OFICIAL | D3: hs | E3: 2 | F3: =50000/8+5789 -> 12039 | G3: =E3*F3 -> 24078
B4: Mano de obra | C4: MEDIO OFICIAL | D4: hs | F4: =45000/8+5789 -> 11414 | G4: =E4*F4 -> 0
B5: Mano de obra | C5: AYUDANTE | D5: hs | E5: 1.2 | F5: =40000/8+5768 -> 10768 | G5: =E5*F5 -> 12921.6
B6: Mano de obra | C6: AYUDA DE GREMIO ayudante | D6: hs | F6: =F5 -> 10768 | G6: =E6*F6 -> 0
B7: SUBTOTAL MANO DE OBRA (A) | G7: =SUM(G2:G6) -> 36999.6
B8: Material | C8: Hierro barra | D8: ton | E8: 0.008 | F8: 1807030 | G8: =E8*F8 -> 14456.24
B9: Material | C9: Alambre negro | D9: kg | E9: 0.01 | F9: 7500 | G9: =E9*F9 -> 75
B10: Material | C10: tablas | D10: m2 | F10: =14500/2.88*3 -> 15104.167 | G10: =E10*F10 -> 0
B11: Material | C11: tirantes | D11: m2 | F11: =12500*3 -> 37500 | G11: =E11*F11 -> 0
B12: Material | C12: clavos | D12: kg | F12: 7500 | G12: =E12*F12 -> 0
B13: Material | C13: cemento | D13: kg | E13: 66 | F13: =13000/50 -> 260 | G13: =E13*F13 -> 17160
B14: Material | C14: arena | D14: m3 | E14: 0.15 | F14: 50000 | G14: =E14*F14 -> 7500
B15: Material | C15: piedra | D15: m3 | E15: 0.18 | F15: 50000 | G15: =E15*F15 -> 9000
B16: Material | G16: =E16*F16 -> 0
B17: Material | G17: =E17*F17 -> 0
B18: Material | G18: =E18*F18 -> 0
B19: Material
B20: Material
B21: Material
B22: SUBTOTAL MATERIAL (B) | G22: =SUM(G8:G21) -> 48191.24
B24: 1 | C24: MANO DE OBRA | D24: TOTAL (A) | G24: =G7 -> 36999.6
B25: 2 | C25: MATERIALES | D25: TOTAL (B) | G25: =G22 -> 48191.24
B26: 3 | C26: EQUIPOS | D26: TOTAL (C)
B27: 4 | C27: COSTO - COSTO | D27: (1 + 2 + 3) | G27: =SUM(G24:G26) -> 85190.84 | I27: =G27*1.95 -> 166122.14
B28: 5 | C28: GASTOS GENERALES | D28: D% x (4) | E28: 0.4 | G28: =+G27*E28 -> 34076.336
B29: 6 | C29: COSTO - COSTO + GASTOS GENERALES | D29: (4 + 5) | G29: =G28+G27 -> 119267.18
B30: 7 | C30: IMPREVISTOS Y EVENTUALIDADES | D30: E% x (6) | E30: 0.1 | G30: =+G29*E30 -> 11926.718
B31: 8 | C31: EPP-SEGURIDAD | D31: F% x (6) | E31: 0.1 | G31: =G29*E31 -> 11926.718
B32: 9 | C32: BENEFICIO | D32: G% x (6) | E32: 0.4 | G32: =G29*E32 -> 47706.87
B33: 10 | C33: COSTO TOTAL DEL TRABAJO | D33: (6 + 7 + 8 + 9) | G33: =G32+G31+G30+G29 -> 190827.48
B34: 11 | C34: COSTO TOTAL DEL TRABAJO SIN MATERIALES | D34: (10 - 1) | G34: =G33-G25 -> 142636.24
B35: 12 | C35: IMPUESTOS (IIBB - GANANCIAS) | D35: V % x (9) | E35: 0 | G35: =G33*E35 -> 0
B36: 13 | C36: GANANCIAS | E36: 0 | G36: =G32*E36 -> 0
B38: 16 | C38: PRECIO UNITARIO DE APLICACIÓN SIN MATERIALES | D38: (10 + 12 + 13) | G38: =G34+G35+G36 -> 142636.24 | I38: 1200 | J38: =G38/I38 -> 118.86353
A40: 1.2 | B40: Partida | C40: CAMARA | D40: m3
B41: Mano de obra | C41: OFICIAL ESPECIALIZADO | D41: hs | E41: 0 | F41: =F2 -> 15789 | G41: =E41*F41 -> 0
B42: Mano de obra | C42: OFICIAL | D42: hs | E42: 35 | F42: =F3 -> 12039 | G42: =E42*F42 -> 421365
B43: Mano de obra | C43: MEDIO OFICIAL | D43: hs | F43: =F4 -> 11414 | G43: =E43*F43 -> 0
B44: Mano de obra | C44: AYUDANTE | D44: hs | E44: 27.6 | F44: =F5 -> 10768 | G44: =E44*F44 -> 297196.8
B45: Mano de obra | C45: AYUDA DE GREMIO ayudante | D45: hs | F45: =F6 -> 10768 | G45: =E45*F45 -> 0
B46: SUBTOTAL MANO DE OBRA (A) | G46: =SUM(G41:G45) -> 718561.8
B47: Material | C47: Hierro barra | D47: ton | E47: 0.09 | F47: 1807030 | G47: =E47*F47 -> 162632.7
B48: Material | C48: Alambre negro | D48: kg | E48: 0.6 | F48: 7500 | G48: =E48*F48 -> 4500
B49: Material | C49: tablas | D49: m2 | E49: 3.3 | F49: =14500/2.88*3 -> 15104.167 | G49: =E49*F49 -> 49843.75
B50: Material | C50: tirantes | D50: m2 | E50: 0.26 | F50: =12500*3 -> 37500 | G50: =E50*F50 -> 9750
B51: Material | C51: clavos | D51: kg | E51: 1.7 | F51: 7500 | G51: =E51*F51 -> 12750
B52: Material | C52: cemento | D52: kg | E52: 330 | F52: =13000/50 -> 260 | G52: =E52*F52 -> 85800
B53: Material | C53: arena | D53: m3 | E53: 0.55 | F53: 50000 | G53: =E53*F53 -> 27500
B54: Material | C54: piedra | D54: m3 | E54: 0.8 | F54: 50000 | G54: =E54*F54 -> 40000
B55: Material | G55: =E55*F55 -> 0
B56: Material | G56: =E56*F56 -> 0
B57: Material | G57: =E57*F57 -> 0
B58: Material
B59: Material
B60: Material
B61: SUBTOTAL MATERIAL (B) | G61: =SUM(G47:G60) -> 392776.45
B63: 1 | C63: MANO DE OBRA | D63: TOTAL (A) | G63: =G46 -> 718561.8
B64: 2 | C64: MATERIALES | D64: TOTAL (B) | G64: =G61 -> 392776.45
B65: 3 | C65: EQUIPOS | D65: TOTAL (C)
B66: 4 | C66: COSTO - COSTO | D66: (1 + 2 + 3) | G66: =SUM(G63:G65) -> 1111338.2 | I66: =G66*1.95 -> 2167109.6
B67: 5 | C67: GASTOS GENERALES | D67: D% x (4) | E67: =E28 -> 0.4 | G67: =+G66*E67 -> 444535.3
B68: 6 | C68: COSTO - COSTO + GASTOS GENERALES | D68: (4 + 5) | G68: =G67+G66 -> 1555873.6
B69: 7 | C69: IMPREVISTOS Y EVENTUALIDADES | D69: E% x (6) | E69: =E30 -> 0.1 | G69: =+G68*E69 -> 155587.36
B70: 8 | C70: EPP-SEGURIDAD | D70: F% x (6) | E70: =E31 -> 0.1 | G70: =G68*E70 -> 155587.36
B71: 9 | C71: BENEFICIO | D71: G% x (6) | E71: =E32 -> 0.4 | G71: =G68*E71 -> 622349.42
B72: 10 | C72: COSTO TOTAL DEL TRABAJO | D72: (6 + 7 + 8 + 9) | G72: =G71+G70+G69+G68 -> 2489397.7
B73: 11 | C73: COSTO TOTAL DEL TRABAJO SIN MATERIALES | D73: (10 - 1) | G73: =G72-G64 -> 2096621.2
B74: 12 | C74: IMPUESTOS (IIBB - GANANCIAS) | D74: V % x (9) | E74: =E35 -> 0 | G74: =G72*E74 -> 0
B75: 13 | C75: GANANCIAS | E75: =E36 -> 0 | G75: =G71*E75 -> 0
B77: 16 | C77: PRECIO UNITARIO DE APLICACIÓN SIN MATERIALES | D77: (10 + 12 + 13) | G77: =G73+G74+G75 -> 2096621.2 | I77: 1200 | J77: =G77/I77 -> 1747.1844
A79: 1.2 | B79: Partida | C79: MOV DE SUELOS BAJO PAVIMENTO | D79: m3
B80: Mano de obra | C80: OFICIAL ESPECIALIZADO | D80: hs | E80: 0 | F80: =F41 -> 15789 | G80: =E80*F80 -> 0
B81: Mano de obra | C81: OFICIAL | D81: hs | E81: 0.08 | F81: =F42 -> 12039 | G81: =E81*F81 -> 963.12
B82: Mano de obra | C82: MEDIO OFICIAL | D82: hs | F82: =F43 -> 11414 | G82: =E82*F82 -> 0
B83: Mano de obra | C83: AYUDANTE | D83: hs | E83: 0.18 | F83: =F44 -> 10768 | G83: =E83*F83 -> 1938.24
B84: Mano de obra | C84: AYUDA DE GREMIO ayudante | D84: hs | F84: =F45 -> 10768 | G84: =E84*F84 -> 0
B85: SUBTOTAL MANO DE OBRA (A) | G85: =SUM(G80:G84) -> 2901.36
B86: Material | G86: =E86*F86 -> 0
B87: Material | G87: =E87*F87 -> 0
B88: Material | G88: =E88*F88 -> 0
B89: Material | G89: =E89*F89 -> 0
B90: Material | G90: =E90*F90 -> 0
B91: Material | G91: =E91*F91 -> 0
B92: Material | G92: =E92*F92 -> 0
B93: Material | G93: =E93*F93 -> 0
B94: Material | G94: =E94*F94 -> 0
B95: Material | G95: =E95*F95 -> 0
B96: Material | G96: =E96*F96 -> 0
B97: Material
B98: Material
B99: Material
B100: SUBTOTAL MATERIAL (B) | G100: =SUM(G86:G99) -> 0
B102: 1 | C102: MANO DE OBRA | D102: TOTAL (A) | G102: =G85 -> 2901.36
B103: 2 | C103: MATERIALES | D103: TOTAL (B) | G103: =G100 -> 0
B104: 3 | C104: EQUIPOS | D104: TOTAL (C) | G104: 7000
B105: 4 | C105: COSTO - COSTO | D105: (1 + 2 + 3) | G105: =SUM(G102:G104) -> 9901.36 | I105: =G105*1.95 -> 19307.652
B106: 5 | C106: GASTOS GENERALES | D106: D% x (4) | E106: =E67 -> 0.4 | G106: =+G105*E106 -> 3960.544
B107: 6 | C107: COSTO - COSTO + GASTOS GENERALES | D107: (4 + 5) | G107: =G106+G105 -> 13861.904
...
